cursor_notebook_mcp/__init__.py
cursor_notebook_mcp/notebook_ops.py
cursor_notebook_mcp/server.py
cursor_notebook_mcp/sftp_manager.py
cursor_notebook_mcp/tools.py
cursor_notebook_mcp-0.3.1.dist-info/METADATA
cursor_notebook_mcp-0.3.1.dist-info/WHEEL
cursor_notebook_mcp-0.3.1.dist-info/entry_points.txt
cursor_notebook_mcp-0.3.1.dist-info/licenses/LICENSE
cursor_notebook_mcp-0.3.1.dist-info/RECORD
