Metadata-Version: 2.4
Name: cursor-notebook-mcp
Version: 0.3.1
Summary: Model Context Protocol (MCP) implementation for Jupyter notebooks to overcome limitation with Cursor
Project-URL: Homepage, https://github.com/jbeno/cursor-notebook-mcp
Project-URL: Bug Tracker, https://github.com/jbeno/cursor-notebook-mcp/issues
Project-URL: Source, https://github.com/jbeno/cursor-notebook-mcp
Author-email: Jim Beno <jim@jimbeno.net>
License: Attribution-NonCommercial-ShareAlike 4.0 International
License-File: LICENSE
Keywords: agent,ai,cursor,ipynb,jupyter,mcp,nbformat,notebook
Classifier: Development Status :: 4 - Beta
Classifier: Framework :: Jupyter
Classifier: Intended Audience :: Developers
Classifier: Intended Audience :: Science/Research
Classifier: License :: Other/Proprietary License
Classifier: Operating System :: OS Independent
Classifier: Programming Language :: Python :: 3
Classifier: Programming Language :: Python :: 3 :: Only
Classifier: Programming Language :: Python :: 3.10
Classifier: Programming Language :: Python :: 3.11
Classifier: Programming Language :: Python :: 3.12
Classifier: Topic :: Scientific/Engineering
Classifier: Topic :: Scientific/Engineering :: Artificial Intelligence
Classifier: Topic :: Software Development :: Libraries :: Python Modules
Classifier: Topic :: Utilities
Classifier: Typing :: Typed
Requires-Python: >=3.10
Requires-Dist: fastmcp<2.11,>=2.7.0
Requires-Dist: ipython
Requires-Dist: jupyter-core
Requires-Dist: mcp>=0.1.0
Requires-Dist: nbconvert>=6.0
Requires-Dist: nbformat>=5.0
Requires-Dist: paramiko>=2.8.0
Requires-Dist: starlette>=0.25.0
Requires-Dist: uvicorn>=0.20.0
Provides-Extra: dev
Requires-Dist: coveralls; extra == 'dev'
Requires-Dist: pytest-asyncio>=0.18; extra == 'dev'
Requires-Dist: pytest-cov; extra == 'dev'
Requires-Dist: pytest-timeout>=2.0.0; extra == 'dev'
Requires-Dist: pytest>=7.0; extra == 'dev'
Provides-Extra: test
Requires-Dist: coveralls; extra == 'test'
Requires-Dist: pytest-asyncio>=0.18; extra == 'test'
Requires-Dist: pytest-cov; extra == 'test'
Requires-Dist: pytest-timeout>=2.0.0; extra == 'test'
Requires-Dist: pytest>=7.0; extra == 'test'
